eval/evaluation.py
nn/activations.py
nn/backpropagation.py
nn/forward.py
nn/layers.py
nn/losses.py
nn/model.py
nn/parameters.py
optim/optimizers.py
utils/dataloader.py
utils/process_tensor.py
utils/transforms.py
viz/visualization.py
pyaroma-0.1.dist-info/METADATA
pyaroma-0.1.dist-info/WHEEL
pyaroma-0.1.dist-info/top_level.txt
pyaroma-0.1.dist-info/RECORD
