Metadata-Version: 2.1
Name: pyaroma
Version: 0.1
Summary: A Framework to for developing Deep Leanring models
Home-page: UNKNOWN
License: UNKNOWN
Platform: UNKNOWN
Classifier: Programming Language :: Python :: 3
Classifier: Programming Language :: Python :: 3.6
Classifier: Programming Language :: Python :: 3.7
Classifier: Operating System :: OS Independent
Requires-Dist: numpy (~=1.19)
Requires-Dist: matplotlib (~=3.3)
Requires-Dist: pandas (~=1.1)
Requires-Dist: kaggle (~=1.5)
Requires-Dist: seaborn (~=0.11)
Provides-Extra: dev
Requires-Dist: tqdm (>=4.50) ; extra == 'dev'
